watermarkpainter.py
watermark_painter-0.0.3.dist-info/METADATA
watermark_painter-0.0.3.dist-info/WHEEL
watermark_painter-0.0.3.dist-info/namespace_packages.txt
watermark_painter-0.0.3.dist-info/top_level.txt
watermark_painter-0.0.3.dist-info/zip-safe
watermark_painter-0.0.3.dist-info/RECORD
